plone.app.jquerytools-1.9.4-py2.7-nspkg.pth
plone/app/jquerytools/__init__.py
plone/app/jquerytools/configure.zcml
plone/app/jquerytools/setuphandlers.py
plone/app/jquerytools/testing.py
plone/app/jquerytools/browser/jquery.form.js
plone/app/jquerytools/browser/jquery.form.min.js
plone/app/jquerytools/browser/jquery.tools.dateinput.css
plone/app/jquerytools/browser/jquery.tools.dateinput.js
plone/app/jquerytools/browser/jquery.tools.dateinput.min.js
plone/app/jquerytools/browser/jquery.tools.js
plone/app/jquerytools/browser/jquery.tools.min.js
plone/app/jquerytools/browser/jquery.tools.plugins.js
plone/app/jquerytools/browser/jquery.tools.plugins.min.js
plone/app/jquerytools/browser/jquery.tools.rangeinput.js
plone/app/jquerytools/browser/jquery.tools.rangeinput.min.js
plone/app/jquerytools/browser/jquery.tools.tooltip.js
plone/app/jquerytools/browser/jquery.tools.tooltip.min.js
plone/app/jquerytools/browser/jquery.tools.tooltip.plugins.js
plone/app/jquerytools/browser/jquery.tools.tooltip.plugins.min.js
plone/app/jquerytools/browser/jquery.tools.validator.js
plone/app/jquerytools/browser/jquery.tools.validator.min.js
plone/app/jquerytools/browser/next.gif
plone/app/jquerytools/browser/overlayhelpers.js
plone/app/jquerytools/browser/overlays.css
plone/app/jquerytools/browser/pb_close.png
plone/app/jquerytools/browser/prev.gif
plone/app/jquerytools/profiles/default/cssregistry.xml
plone/app/jquerytools/profiles/default/is_jquerytools_profile.txt
plone/app/jquerytools/profiles/default/jsregistry.xml
plone/app/jquerytools/profiles/default/metadata.xml
plone/app/jquerytools/tests/__init__.py
plone/app/jquerytools/tests/browser.py
plone/app/jquerytools/tests/configure.zcml
plone/app/jquerytools/tests/ploneIntegration.txt
plone/app/jquerytools/tests/testsDocTests.py
plone/app/jquerytools/tests/selenium/README.txt
plone/app/jquerytools/tests/selenium/__init__.py
plone/app/jquerytools/tests/selenium/base.py
plone.app.jquerytools-1.9.4.dist-info/DESCRIPTION.rst
plone.app.jquerytools-1.9.4.dist-info/METADATA
plone.app.jquerytools-1.9.4.dist-info/RECORD
plone.app.jquerytools-1.9.4.dist-info/WHEEL
plone.app.jquerytools-1.9.4.dist-info/entry_points.txt
plone.app.jquerytools-1.9.4.dist-info/metadata.json
plone.app.jquerytools-1.9.4.dist-info/namespace_packages.txt
plone.app.jquerytools-1.9.4.dist-info/top_level.txt
