Metadata-Version: 2.0
Name: plone.app.jquerytools
Version: 1.9.4
Summary: jQuery Tools integration for Plone plus overlay and AJAX form helpers.
Home-page: http://pypi.python.org/pypi/plone.app.jquerytools
Author: Plone Foundation
Author-email: plone-developers@lists.sourceforge.net
License: GPL version 2
Keywords: Plone jQuery overlays AJAX
Platform: UNKNOWN
Classifier: Environment :: Web Environment
Classifier: Framework :: Plone
Classifier: Framework :: Plone :: 4.3
Classifier: Framework :: Zope2
Classifier: License :: OSI Approved :: GNU General Public License (GPL)
Classifier: Operating System :: OS Independent
Classifier: Programming Language :: Python
Classifier: Programming Language :: Python :: 2.6
Classifier: Programming Language :: Python :: 2.7
Requires-Dist: setuptools
Requires-Dist: zope.component
Requires-Dist: Products.CMFCore
Requires-Dist: Products.GenericSetup
Requires-Dist: Zope2
Provides-Extra: test
Requires-Dist: plone.app.testing; extra == 'test'
Requires-Dist: selenium; extra == 'test'
